stock_service/__init__.py
stock_service/config.py
stock_service/errors.py
stock_service/service.py
stock_service/backports/__init__.py
stock_service/backports/cached_property.py
stock_service/consumers/__init__.py
stock_service/consumers/send_legacy_stock_adjustment_event.py
stock_service/consumers/update_merchant_offer_service.py
stock_service/consumers/update_stock_consumer.py
stock_service/controllers/__init__.py
stock_service/controllers/adjustment_controller.py
stock_service/controllers/consumer_health_controller.py
stock_service/controllers/inventory_controller.py
stock_service/controllers/owner_controller.py
stock_service/controllers/service_health_controller.py
stock_service/controllers/stock_adjustment_controller.py
stock_service/controllers/stock_controller.py
stock_service/controllers/stock_snapshot_controller.py
stock_service/controllers/stock_status_controller.py
stock_service/external/__init__.py
stock_service/external/merchant_offers.py
stock_service/external/merchant_returns.py
stock_service/managers/__init__.py
stock_service/managers/takealot_stock_management.py
stock_service/managers/update_stock_managers.py
stock_service/models/__init__.py
stock_service/models/base_model.py
stock_service/models/company.py
stock_service/models/inventory.py
stock_service/models/location.py
stock_service/models/owner.py
stock_service/models/stock.py
stock_service/models/stock_level.py
stock_service/models/stock_status.py
stock_service/models/take2/__init__.py
stock_service/models/take2/schema.py
stock_service/models/take2/stock.py
stock_service/models/take2/stock_adjustment.py
stock_service/models/take2/stock_snapshot.py
stock_service/models/take2/warehouse.py
stock_service/producers/__init__.py
stock_service/producers/base.py
stock_service/producers/stock_adjustment_producers.py
stock_service/producers/stock_producer.py
stock_service/stock_management/__init__.py
stock_service/stock_management/adjustment.py
stock_service/utils/__init__.py
stock_service/utils/db.py
stock_service-0.2.112rc0.dist-info/METADATA
stock_service-0.2.112rc0.dist-info/WHEEL
stock_service-0.2.112rc0.dist-info/entry_points.txt
stock_service-0.2.112rc0.dist-info/top_level.txt
stock_service-0.2.112rc0.dist-info/RECORD
