Metadata-Version: 2.1
Name: stock-service
Version: 0.2.112rc0
Summary: Service to centralise stock levels.
Home-page: https://github.com/TAKEALOT/stock-service
Author: WMS
Author-email: en-log@takealot.com
License: UNKNOWN
Keywords: stock
Platform: UNKNOWN
Classifier: Programming Language :: Python
Requires-Python: >= 3
Requires-Dist: cachetools (==4.0.0)
Requires-Dist: click (==6.7)
Requires-Dist: flake8 (==4.0.1)
Requires-Dist: protobuf (<4,>=3)
Requires-Dist: pykafka (==2.6.0)
Requires-Dist: requests (==2.27.0)
Requires-Dist: requests-toolbelt (==0.9.1)
Requires-Dist: SQLAlchemy-Utils (==0.36.1)
Requires-Dist: coverage (==5.0.3)
Requires-Dist: retry (==0.9.2)
Requires-Dist: sentry-sdk (==0.16.5)
Requires-Dist: cache-client (<3.1.0,>=3.0.1)
Requires-Dist: merchant-returns-service-client (==1.0.20)
Requires-Dist: s4f-clients (==2.15.7)
Requires-Dist: sql-client (==0.3.3)
Requires-Dist: tal-kafka (==3.0.3)
Requires-Dist: tal-schema-registry (>=0.11.26)
Requires-Dist: tal-service-config (==3.3.1)
Requires-Dist: tal-stats-client (==0.2.5)
Requires-Dist: rest-clients (==4.33.27)
Provides-Extra: test
Requires-Dist: hypothesis (==5.5.3) ; extra == 'test'
Requires-Dist: parameterized (==0.7.4) ; extra == 'test'
Requires-Dist: mock ; extra == 'test'
Requires-Dist: psycopg2 ; extra == 'test'
Requires-Dist: pytest (==5.3.5) ; extra == 'test'
Requires-Dist: sqlalchemy ; extra == 'test'
